README.rst
setup.py
contacthub/__init__.py
contacthub/node.py
contacthub/workspace.py
contacthub/_api_manager/__init__.py
contacthub/_api_manager/_api_customer.py
contacthub/_api_manager/_api_event.py
contacthub/_parsers/__init__.py
contacthub/_parsers/_config_parser.py
contacthub/errors/__init__.py
contacthub/errors/api_error.py
contacthub/errors/operation_not_permitted.py
contacthub/lib/__init__.py
contacthub/lib/paginated_list.py
contacthub/lib/read_only_list.py
contacthub/lib/utils.py
contacthub/models/__init__.py
contacthub/models/customer.py
contacthub/models/education.py
contacthub/models/event.py
contacthub/models/job.py
contacthub/models/like.py
contacthub/models/properties.py
contacthub/models/subscription.py
contacthub/models/query/__init__.py
contacthub/models/query/criterion.py
contacthub/models/query/entity_field.py
contacthub/models/query/entity_meta.py
contacthub/models/query/query.py
contacthub_sdk_python.egg-info/PKG-INFO
contacthub_sdk_python.egg-info/SOURCES.txt
contacthub_sdk_python.egg-info/dependency_links.txt
contacthub_sdk_python.egg-info/not-zip-safe
contacthub_sdk_python.egg-info/requires.txt
contacthub_sdk_python.egg-info/top_level.txt