Metadata-Version: 1.1
Name: contacthub-sdk-python
Version: 0.2
Summary: This is the official Python SDK for Contacthub REST API. This SDK easily allows to access your data on Contacthub, making the authentication immediate and simplifying read/write operations.
Home-page: https://github.com/contactlab/contacthub-sdk-python
Author: Contactlab
Author-email: developer@contactlab.com
License: UNKNOWN
Keywords: web skd api
Platform: UNKNOWN
Classifier: Intended Audience :: Developers
Classifier: Programming Language :: Python
Classifier: Programming Language :: Python :: 2.6
Classifier: Programming Language :: Python :: 2.7
Classifier: Programming Language :: Python :: 3.3
Classifier: Programming Language :: Python :: 3.4
Classifier: Programming Language :: Python :: 3.5
Classifier: Programming Language :: Python :: 3.6
Classifier: Topic :: Internet :: WWW/HTTP
Classifier: Topic :: Software Development :: Libraries :: Python Modules
Classifier: Intended Audience :: Customer Service
Classifier: Intended Audience :: Developers
Classifier: Development Status :: 5 - Production/Stable
